tokko_auth/__init__.py
tokko_auth/admin.py
tokko_auth/apps.py
tokko_auth/constants.py
tokko_auth/decorators.py
tokko_auth/exceptions.py
tokko_auth/helpers.py
tokko_auth/middleware.py
tokko_auth/models.py
tokko_auth/settings.py
tokko_auth/tools.py
tokko_auth/tools_deprecated.py
tokko_auth/tools_old.py
tokko_auth/urls.py
tokko_auth/util.py
tokko_auth/views.py
tokko_auth/future/__init__.py
tokko_auth/future/encodings.py
tokko_auth/future/tests.py
tokko_auth/future/tools/__init__.py
tokko_auth/future/tools/permissions.py
tokko_auth/future/tools/testing.py
tokko_auth/future/tools/validation.py
tokko_auth/lambdas/__init__.py
tokko_auth/lambdas/permission_crud.py
tokko_auth/migrations/__init__.py
tokko_auth/tests/__init__.py
tokko_auth/tests/context.py
tokko_auth/tests/crypto.py
tokko_auth/tests/schema.py
tokko_auth/tests/service.py
tokko_auth/tests/unit.py
tokko_auth/tools/__init__.py
tokko_auth/tools/testing.py
tokko_auth/tools/validation.py
tokko_auth-0.2.2.dist-info/METADATA
tokko_auth-0.2.2.dist-info/WHEEL
tokko_auth-0.2.2.dist-info/top_level.txt
tokko_auth-0.2.2.dist-info/RECORD
