Metadata-Version: 2.1
Name: tokko-auth
Version: 0.2.2
Summary: Tokko Auth2 flavor.
Home-page: https://github.com/TokkoLabs/services-tokkobroker/libraries/tokko_auth_lib
Author: Tokko Labs
Author-email: devs@tokkobroker.com
License: BSD License
Platform: UNKNOWN
Classifier: Environment :: Web Environment
Classifier: Intended Audience :: Developers
Classifier: License :: OSI Approved :: BSD License
Classifier: Operating System :: OS Independent
Classifier: Programming Language :: Python
Classifier: Programming Language :: Python :: 3.8
Classifier: Topic :: Internet :: WWW/HTTP
Classifier: Topic :: Internet :: WWW/HTTP :: Dynamic Content
Requires-Dist: PyCryptodome
Requires-Dist: arrow
Requires-Dist: pycrypto
Requires-Dist: pyjwt
Requires-Dist: python-jose
Requires-Dist: python-jwt
